pyspapi/__init__.py
pyspapi/api/__init__.py
pyspapi/api/api.py
pyspapi/exceptions.py
pyspapi/spworlds.py
pyspapi/types/__init__.py
pyspapi/types/me.py
pyspapi/types/payment.py
pyspapi/types/users.py
pyspapi-3.3.1.dist-info/METADATA
pyspapi-3.3.1.dist-info/WHEEL
pyspapi-3.3.1.dist-info/licenses/LICENSE
pyspapi-3.3.1.dist-info/RECORD
