Metadata-Version: 2.4
Name: pyspapi
Version: 3.3.1
Summary: API wrapper for SP servers written in Python.
License: MIT
License-File: LICENSE
Author: deesiigneer
Author-email: xdeesiigneerx@gmail.com
Requires-Python: >=3.12,<3.15
Classifier: License :: OSI Approved :: MIT License
Classifier: Programming Language :: Python :: 3
Classifier: Programming Language :: Python :: 3.12
Classifier: Programming Language :: Python :: 3.13
Classifier: Programming Language :: Python :: 3.14
Provides-Extra: dev
Provides-Extra: docs
Requires-Dist: aiohttp (>=3.9,<4.0)
Requires-Dist: pydata-sphinx-theme (>=0.16.1,<0.17.0) ; extra == "docs"
Requires-Dist: ruff (>=0.14,<0.15) ; extra == "dev"
Requires-Dist: sphinx (>=7,<9) ; extra == "docs"
Requires-Dist: sphinx-autobuild (>=2025.8.25,<2026.0.0) ; extra == "docs"
Requires-Dist: toml-sort (>=0.24,<0.25) ; extra == "dev"
Project-URL: Documentation, https://pyspapi.readthedocs.org
Project-URL: Discord, https://discord.com/invite/VbyHaKRAaN
Project-URL: Homepage, https://pyspapi.deesiigneer.ru
Project-URL: Issue Tracker, https://github.com/deesiigneer/pyspapi/issues
Project-URL: Repository, https://github.com/deesiigneer/pyspapi
